exoplanet_core/exoplanet_core_version.py
exoplanet_core/core.py
exoplanet_core/testing.py
exoplanet_core/driver.cpython-39-x86_64-linux-gnu.so
exoplanet_core/driver.cpp
exoplanet_core/__init__.py
exoplanet_core/pymc3/ops.py
exoplanet_core/pymc3/__init__.py
exoplanet_core/numpy/ops.py
exoplanet_core/numpy/__init__.py
exoplanet_core/lib/include/exoplanet/ellip.h
exoplanet_core/lib/include/exoplanet/limbdark.h
exoplanet_core/lib/include/exoplanet/exoplanet.h
exoplanet_core/lib/include/exoplanet/contact_points.h
exoplanet_core/lib/include/exoplanet/kepler.h
exoplanet_core/lib/include/exoplanet/constants.h
exoplanet_core/jax/ops.py
exoplanet_core/jax/gpu_driver.cpp
exoplanet_core/jax/kernel_helpers.h
exoplanet_core/jax/pybind11_kernel_helpers.h
exoplanet_core/jax/cpu_driver.cpython-39-x86_64-linux-gnu.so
exoplanet_core/jax/cpu_driver.cpp
exoplanet_core/jax/cuda_kernels.cc.cu
exoplanet_core/jax/__init__.py
exoplanet_core/jax/cuda_kernels.h
exoplanet_core/pymc/ops.py
exoplanet_core/pymc/jax_support.py
exoplanet_core/pymc/__init__.py
exoplanet_core-0.3.0.dist-info/LICENSE
exoplanet_core-0.3.0.dist-info/RECORD
exoplanet_core-0.3.0.dist-info/METADATA
exoplanet_core-0.3.0.dist-info/WHEEL
exoplanet_core-0.3.0.dist-info/top_level.txt
