Metadata-Version: 2.1
Name: exoplanet_core
Version: 0.3.0
Summary: The compiled backend for exoplanet
Home-page: https://docs.exoplanet.codes
Author: Daniel Foreman-Mackey
Author-email: foreman.mackey@gmail.com
Maintainer: Daniel Foreman-Mackey
Maintainer-email: foreman.mackey@gmail.com
License: MIT
Classifier: Development Status :: 4 - Beta
Classifier: Intended Audience :: Developers
Classifier: Intended Audience :: Science/Research
Classifier: License :: OSI Approved :: MIT License
Classifier: Operating System :: OS Independent
Classifier: Programming Language :: Python
Classifier: Programming Language :: Python :: 3
License-File: LICENSE
Requires-Dist: numpy >=1.13.0
Provides-Extra: benchmark
Requires-Dist: pytest ; extra == 'benchmark'
Requires-Dist: pytest-benchmark ; extra == 'benchmark'
Requires-Dist: radvel ; extra == 'benchmark'
Requires-Dist: kepler.py ; extra == 'benchmark'
Requires-Dist: batman-package ; extra == 'benchmark'
Requires-Dist: starry ; extra == 'benchmark'
Requires-Dist: exoplanet ==0.4.5 ; extra == 'benchmark'
Provides-Extra: comparison
Requires-Dist: batman-package ; extra == 'comparison'
Requires-Dist: starry ; extra == 'comparison'
Requires-Dist: numpy <1.22 ; extra == 'comparison'
Requires-Dist: xarray <2023.10.0 ; extra == 'comparison'
Provides-Extra: jax
Requires-Dist: jax ; extra == 'jax'
Requires-Dist: jaxlib ; extra == 'jax'
Provides-Extra: pymc
Requires-Dist: pymc >=5.0.0 ; extra == 'pymc'
Provides-Extra: pymc3
Requires-Dist: pymc3 >=3.9 ; extra == 'pymc3'
Requires-Dist: numpy <1.22 ; extra == 'pymc3'
Provides-Extra: test
Requires-Dist: pytest ; extra == 'test'
